{
  "metadata": {
    "generated_at": "2025-12-04T14:21:19.358002Z",
    "lat": 40.71,
    "lon": -74.0,
    "days_requested": 7,
    "sources": [
      "TWC",
      "NWS"
    ],
    "attribution": {
      "TWC": "Data courtesy The Weather Company / weather.com",
      "NWS": "Data courtesy National Weather Service"
    }
  },
  "twc_daily": [
    {
      "validTimeUtc": 1764849600,
      "validTimeIso": "2025-12-04T12:00:00Z",
      "dayOfWeek": "Thursday",
      "tempMax_F": 44,
      "tempMin_F": 23,
      "qpf_in": 0.0,
      "narrative": "Clouds giving way to sun . Highs in the mid 40s and lows in the low 20s."
    },
    {
      "validTimeUtc": 1764936000,
      "validTimeIso": "2025-12-05T12:00:00Z",
      "dayOfWeek": "Friday",
      "tempMax_F": 33,
      "tempMin_F": 31,
      "qpf_in": 0.0,
      "narrative": "Mix of sun and clouds. Highs in the low 30s with temperatures nearly steady overnight."
    },
    {
      "validTimeUtc": 1765022400,
      "validTimeIso": "2025-12-06T12:00:00Z",
      "dayOfWeek": "Saturday",
      "tempMax_F": 42,
      "tempMin_F": 33,
      "qpf_in": 0.0,
      "narrative": "More clouds than sun. Highs in the low 40s and lows in the low 30s."
    },
    {
      "validTimeUtc": 1765108800,
      "validTimeIso": "2025-12-07T12:00:00Z",
      "dayOfWeek": "Sunday",
      "tempMax_F": 44,
      "tempMin_F": 32,
      "qpf_in": 0.0,
      "narrative": "Times of sun and clouds. Highs in the mid 40s and lows in the low 30s."
    },
    {
      "validTimeUtc": 1765195200,
      "validTimeIso": "2025-12-08T12:00:00Z",
      "dayOfWeek": "Monday",
      "tempMax_F": 36,
      "tempMin_F": 20,
      "qpf_in": 0.0,
      "narrative": "Abundant sunshine. Highs in the mid 30s and lows in the low 20s."
    },
    {
      "validTimeUtc": 1765281600,
      "validTimeIso": "2025-12-09T12:00:00Z",
      "dayOfWeek": "Tuesday",
      "tempMax_F": 36,
      "tempMin_F": 32,
      "qpf_in": 0.0,
      "narrative": "Times of sun and clouds. Highs in the mid 30s and lows in the low 30s."
    },
    {
      "validTimeUtc": 1765368000,
      "validTimeIso": "2025-12-10T12:00:00Z",
      "dayOfWeek": "Wednesday",
      "tempMax_F": 44,
      "tempMin_F": 40,
      "qpf_in": 0.05,
      "narrative": "Considerable cloudiness. Highs in the mid 40s and lows in the low 40s."
    }
  ],
  "nws_periods": [
    {
      "number": 1,
      "name": "Today",
      "startTime": "2025-12-04T07:00:00-05:00",
      "endTime": "2025-12-04T18:00:00-05:00",
      "isDaytime": true,
      "temperature": 41,
      "temperatureUnit": "F",
      "temperatureTrend": null,
      "probabilityOfPrecipitation": {
        "unitCode": "wmoUnit:percent",
        "value": 10
      },
      "windSpeed": "12 to 24 mph",
      "windDirection": "W",
      "icon": "https://api.weather.gov/icons/land/day/wind_bkn?size=medium",
      "shortForecast": "Partly Sunny",
      "detailedForecast": "Partly sunny. High near 41, with temperatures falling to around 38 in the afternoon. West wind 12 to 24 mph, with gusts as high as 35 mph."
    },
    {
      "number": 2,
      "name": "Tonight",
      "startTime": "2025-12-04T18:00:00-05:00",
      "endTime": "2025-12-05T06:00:00-05:00",
      "isDaytime": false,
      "temperature": 22,
      "temperatureUnit": "F",
      "temperatureTrend": null,
      "probabilityOfPrecipitation": {
        "unitCode": "wmoUnit:percent",
        "value": 0
      },
      "windSpeed": "8 to 25 mph",
      "windDirection": "NW",
      "icon": "https://api.weather.gov/icons/land/night/wind_few?size=medium",
      "shortForecast": "Mostly Clear",
      "detailedForecast": "Mostly clear, with a low around 22. Wind chill values as low as 13. Northwest wind 8 to 25 mph, with gusts as high as 36 mph."
    },
    {
      "number": 3,
      "name": "Friday",
      "startTime": "2025-12-05T06:00:00-05:00",
      "endTime": "2025-12-05T18:00:00-05:00",
      "isDaytime": true,
      "temperature": 35,
      "temperatureUnit": "F",
      "temperatureTrend": null,
      "probabilityOfPrecipitation": {
        "unitCode": "wmoUnit:percent",
        "value": 21
      },
      "windSpeed": "7 mph",
      "windDirection": "E",
      "icon": "https://api.weather.gov/icons/land/day/sct/snow,20?size=medium",
      "shortForecast": "Mostly Sunny then Slight Chance Very Light Snow",
      "detailedForecast": "A slight chance of snow after 4pm. Mostly sunny. High near 35, with temperatures falling to around 33 in the afternoon. Wind chill values as low as 14. East wind around 7 mph. Chance of precipitation is 20%."
    },
    {
      "number": 4,
      "name": "Friday Night",
      "startTime": "2025-12-05T18:00:00-05:00",
      "endTime": "2025-12-06T06:00:00-05:00",
      "isDaytime": false,
      "temperature": 30,
      "temperatureUnit": "F",
      "temperatureTrend": null,
      "probabilityOfPrecipitation": {
        "unitCode": "wmoUnit:percent",
        "value": 37
      },
      "windSpeed": "6 mph",
      "windDirection": "NW",
      "icon": "https://api.weather.gov/icons/land/night/snow,40?size=medium",
      "shortForecast": "Chance Very Light Snow",
      "detailedForecast": "A chance of snow. Mostly cloudy. Low around 30, with temperatures rising to around 35 overnight. Northwest wind around 6 mph. Chance of precipitation is 40%."
    },
    {
      "number": 5,
      "name": "Saturday",
      "startTime": "2025-12-06T06:00:00-05:00",
      "endTime": "2025-12-06T18:00:00-05:00",
      "isDaytime": true,
      "temperature": 41,
      "temperatureUnit": "F",
      "temperatureTrend": null,
      "probabilityOfPrecipitation": {
        "unitCode": "wmoUnit:percent",
        "value": 26
      },
      "windSpeed": "8 mph",
      "windDirection": "NW",
      "icon": "https://api.weather.gov/icons/land/day/snow,30/bkn?size=medium",
      "shortForecast": "Chance Very Light Snow then Partly Sunny",
      "detailedForecast": "A chance of snow before 10am. Partly sunny, with a high near 41. Northwest wind around 8 mph. Chance of precipitation is 30%."
    },
    {
      "number": 6,
      "name": "Saturday Night",
      "startTime": "2025-12-06T18:00:00-05:00",
      "endTime": "2025-12-07T06:00:00-05:00",
      "isDaytime": false,
      "temperature": 30,
      "temperatureUnit": "F",
      "temperatureTrend": null,
      "probabilityOfPrecipitation": {
        "unitCode": "wmoUnit:percent",
        "value": 6
      },
      "windSpeed": "8 mph",
      "windDirection": "W",
      "icon": "https://api.weather.gov/icons/land/night/sct?size=medium",
      "shortForecast": "Partly Cloudy",
      "detailedForecast": "Partly cloudy, with a low around 30."
    },
    {
      "number": 7,
      "name": "Sunday",
      "startTime": "2025-12-07T06:00:00-05:00",
      "endTime": "2025-12-07T18:00:00-05:00",
      "isDaytime": true,
      "temperature": 41,
      "temperatureUnit": "F",
      "temperatureTrend": null,
      "probabilityOfPrecipitation": {
        "unitCode": "wmoUnit:percent",
        "value": 4
      },
      "windSpeed": "8 mph",
      "windDirection": "NW",
      "icon": "https://api.weather.gov/icons/land/day/bkn?size=medium",
      "shortForecast": "Partly Sunny",
      "detailedForecast": "Partly sunny, with a high near 41."
    },
    {
      "number": 8,
      "name": "Sunday Night",
      "startTime": "2025-12-07T18:00:00-05:00",
      "endTime": "2025-12-08T06:00:00-05:00",
      "isDaytime": false,
      "temperature": 27,
      "temperatureUnit": "F",
      "temperatureTrend": null,
      "probabilityOfPrecipitation": {
        "unitCode": "wmoUnit:percent",
        "value": 12
      },
      "windSpeed": "8 to 14 mph",
      "windDirection": "NW",
      "icon": "https://api.weather.gov/icons/land/night/bkn?size=medium",
      "shortForecast": "Mostly Cloudy",
      "detailedForecast": "Mostly cloudy, with a low around 27."
    },
    {
      "number": 9,
      "name": "Monday",
      "startTime": "2025-12-08T06:00:00-05:00",
      "endTime": "2025-12-08T18:00:00-05:00",
      "isDaytime": true,
      "temperature": 29,
      "temperatureUnit": "F",
      "temperatureTrend": null,
      "probabilityOfPrecipitation": {
        "unitCode": "wmoUnit:percent",
        "value": 11
      },
      "windSpeed": "15 mph",
      "windDirection": "N",
      "icon": "https://api.weather.gov/icons/land/day/sct?size=medium",
      "shortForecast": "Mostly Sunny",
      "detailedForecast": "Mostly sunny, with a high near 29."
    },
    {
      "number": 10,
      "name": "Monday Night",
      "startTime": "2025-12-08T18:00:00-05:00",
      "endTime": "2025-12-09T06:00:00-05:00",
      "isDaytime": false,
      "temperature": 23,
      "temperatureUnit": "F",
      "temperatureTrend": null,
      "probabilityOfPrecipitation": {
        "unitCode": "wmoUnit:percent",
        "value": 3
      },
      "windSpeed": "8 to 12 mph",
      "windDirection": "NW",
      "icon": "https://api.weather.gov/icons/land/night/sct?size=medium",
      "shortForecast": "Partly Cloudy",
      "detailedForecast": "Partly cloudy, with a low around 23."
    },
    {
      "number": 11,
      "name": "Tuesday",
      "startTime": "2025-12-09T06:00:00-05:00",
      "endTime": "2025-12-09T18:00:00-05:00",
      "isDaytime": true,
      "temperature": 36,
      "temperatureUnit": "F",
      "temperatureTrend": null,
      "probabilityOfPrecipitation": {
        "unitCode": "wmoUnit:percent",
        "value": 12
      },
      "windSpeed": "7 to 10 mph",
      "windDirection": "SW",
      "icon": "https://api.weather.gov/icons/land/day/bkn?size=medium",
      "shortForecast": "Partly Sunny",
      "detailedForecast": "Partly sunny, with a high near 36."
    },
    {
      "number": 12,
      "name": "Tuesday Night",
      "startTime": "2025-12-09T18:00:00-05:00",
      "endTime": "2025-12-10T06:00:00-05:00",
      "isDaytime": false,
      "temperature": 33,
      "temperatureUnit": "F",
      "temperatureTrend": null,
      "probabilityOfPrecipitation": {
        "unitCode": "wmoUnit:percent",
        "value": 27
      },
      "windSpeed": "12 mph",
      "windDirection": "SW",
      "icon": "https://api.weather.gov/icons/land/night/snow,30?size=medium",
      "shortForecast": "Chance Light Snow",
      "detailedForecast": "A chance of snow after 7pm. Mostly cloudy, with a low around 33. Chance of precipitation is 30%."
    },
    {
      "number": 13,
      "name": "Wednesday",
      "startTime": "2025-12-10T06:00:00-05:00",
      "endTime": "2025-12-10T18:00:00-05:00",
      "isDaytime": true,
      "temperature": 42,
      "temperatureUnit": "F",
      "temperatureTrend": null,
      "probabilityOfPrecipitation": {
        "unitCode": "wmoUnit:percent",
        "value": 27
      },
      "windSpeed": "12 mph",
      "windDirection": "SW",
      "icon": "https://api.weather.gov/icons/land/day/snow,20/snow,30?size=medium",
      "shortForecast": "Slight Chance Light Snow then Chance Rain And Snow",
      "detailedForecast": "A slight chance of snow before 7am, then a chance of rain and snow. Mostly cloudy, with a high near 42. Chance of precipitation is 30%."
    },
    {
      "number": 14,
      "name": "Wednesday Night",
      "startTime": "2025-12-10T18:00:00-05:00",
      "endTime": "2025-12-11T06:00:00-05:00",
      "isDaytime": false,
      "temperature": 38,
      "temperatureUnit": "F",
      "temperatureTrend": null,
      "probabilityOfPrecipitation": {
        "unitCode": "wmoUnit:percent",
        "value": 47
      },
      "windSpeed": "12 mph",
      "windDirection": "SW",
      "icon": "https://api.weather.gov/icons/land/night/rain,40/rain,50?size=medium",
      "shortForecast": "Chance Light Rain",
      "detailedForecast": "A chance of rain. Mostly cloudy, with a low around 38."
    }
  ]
}