{
    "storms": {
        "[0]": {
            "basin": "West Pacific",
            "basinAbbreviation": "WP",
            "name": "Fung-Wong",
            "intensity": "Tropical Storm",
            "intensityAbbreviation": "TS",
            "sustainedWinds": "35 mph",
            "sustainedGusts": "45 mph",
            "position": "25.8\u00b0N, 125.3\u00b0E",
            "movementSpeed": "27 mph",
            "lastUpdate": "2025-11-13T09:00:00Z",
            "issuedBy": "JTWC",
            "issuedByFormal": "Joint Typhoon Warning Center",
            "movementDirection": "60",
            "movementCardinal": "ENE",
            "movementDegrees": "60",
            "stormNumber": "32",
            "stormBaroPressure": null,
            "stormBaroMillibars": null,
            "stormId": "WP322025",
            "forecastCone": {
                "comment": "Sample Code, expect a bunch of pairs of coordinates here soon :)"
            },
            "apiCourtesy": "TWC, JesseLikesWeather"
        }
    }
}